{"schemaVersion":1,"id":"cinderwell_yard","name":"Cinderwell Yard","scene":"Zone_CampaignWorld","levelBand":[1,3],"encounters":[{"id":"enc_cinderwell_yard_cordon","units":["goblin","goblin","marsh_skulker"],"requiredForClear":true},{"id":"enc_cinderwell_yard_well","units":["marsh_skulker","marsh_skulker","goblin"],"requiredForClear":true},{"id":"enc_cinderwell_yard_captain","units":["orc","goblin","goblin"],"requiredForClear":true}],"clearQuest":"q_cinderwell_raider","onCleared":{"pacify":true}}
