{"schemaVersion":1,"id":"emberwild_expanse","name":"The Emberwild Expanse","scene":"Zone_CampaignWorld","levelBand":[2,5],"encounters":[{"id":"enc_emberwild_expanse_trail","units":["giant_spider","giant_spider"],"requiredForClear":true},{"id":"enc_emberwild_expanse_crossing","units":["brown_bear","goblin","goblin"],"requiredForClear":true},{"id":"enc_emberwild_expanse_vessel","units":["brown_bear","giant_spider","giant_spider"],"requiredForClear":true}],"clearQuest":"q_ember_vessel","onCleared":{"pacify":true}}
