{"schemaVersion":1,"id":"tidebreaker_anchorage","name":"Tidebreaker Anchorage","scene":"Zone_CampaignWorld","levelBand":[3,5],"encounters":[{"id":"enc_tidebreaker_anchorage_shipyard","units":["marsh_skulker","marsh_skulker","orc"],"requiredForClear":true},{"id":"enc_tidebreaker_anchorage_stockade","units":["orc","orc","marsh_skulker"],"requiredForClear":true},{"id":"enc_tidebreaker_anchorage_flagship","units":["orc_warchief","orc","marsh_skulker"],"requiredForClear":true}],"clearQuest":"q_rescue_tidebreaker_heir","onCleared":{"pacify":true}}
